{"_ts":[1551420287,1551464151],"_r":{"breakdown":{"html":{"bytes":[4141,4139],"requests":[2,2]},"js":{"bytes":[9345,9345],"requests":[2,2]},"css":{"bytes":[1439,1439],"requests":[1,1]},"image":{"bytes":[1269,1269],"requests":[1,1]},"flash":{"bytes":[0,0],"requests":[0,0]},"font":{"bytes":[75860,75860],"requests":[2,2]},"video":{"bytes":[0,0],"requests":[0,0]},"other":{"bytes":[0,0],"requests":[0,0]}},"date":[1551420287,1551464151],"domElements":[27,27],"domInteractive":[551,557],"firstPaint":[666.6600000026,679.5700000002],"fullyLoaded":[1485,1439],"id":["190301_P1_57d0818bf9ecfad2bf4b410885402f82","190301_17_12078920d0806f9e5cbf06cae1f8c710"],"loadTime":[624,629],"render":[700,700],"SpeedIndex":[717,717],"TTFB":[527,536],"videoFrames":[[{"_i":"ms_000000.jpg","_t":0,"_vc":0},{"_i":"ms_000700.jpg","_t":700,"_vc":94},{"_i":"ms_000900.jpg","_t":900,"_vc":95},{"_i":"ms_001000.jpg","_t":1000,"_vc":100}],[{"_i":"ms_000000.jpg","_t":0,"_vc":0},{"_i":"ms_000700.jpg","_t":700,"_vc":94},{"_i":"ms_000900.jpg","_t":900,"_vc":95},{"_i":"ms_001000.jpg","_t":1000,"_vc":100}]],"visualComplete":[1000,1000],"lighthouse":[57,57],"pagespeed":[97,97]}}